mypackage/__init__.py
mypackage/__version__.py
mypackage/core.py
nblogic/__init__.py
nblogic/__version__.py
nblogic/icit_grade.py
nblogic/klogic_gpa.py
nblogic-1.0.20.dist-info/METADATA
nblogic-1.0.20.dist-info/RECORD
nblogic-1.0.20.dist-info/WHEEL
nblogic-1.0.20.dist-info/top_level.txt
