Metadata-Version: 2.1
Name: nblogic
Version: 1.0.20
Summary: NBLOGIC for the win
Home-page: UNKNOWN
Author: Thanawat Petchuen
Author-email: thanawat1petchuen@gmail.com
License: MIT
Platform: UNKNOWN
Classifier: License :: OSI Approved :: MIT License
Classifier: Programming Language :: Python
Classifier: Programming Language :: Python :: 3
Classifier: Programming Language :: Python :: 3.6
Classifier: Programming Language :: Python :: Implementation :: CPython
Classifier: Programming Language :: Python :: Implementation :: PyPy
Requires-Python: >=3.6.0
Requires-Dist: art
Requires-Dist: mechanicalsoup
